{
  "title": "Atomic Habits",
  "description": "Notes from the Atomic Habits book",
  "date": "2021-01-19",
  "tags": [
    {
      "href": "/tags/bookshelf",
      "name": "bookshelf"
    },
    {
      "href": "/tags/lifestyle-design",
      "name": "lifestyle_design"
    }
  ],
  "coverImage": {
    "src": "/bookshelf/atomic-habits/cover.jpeg",
    "width": "592",
    "height": "375",
    "alt": "The Atomic Habits book",
    "authorHref": "https://jamesclear.com/atomic-habits",
    "authorName": "James Clear"
  }
}
